pyrecog/__init__.py
pyrecog/main.py
pyrecog-1.0.6.dist-info/LICENSE.txt
pyrecog-1.0.6.dist-info/METADATA
pyrecog-1.0.6.dist-info/WHEEL
pyrecog-1.0.6.dist-info/top_level.txt
pyrecog-1.0.6.dist-info/RECORD
